tapioca_the_moviedb/__init__.py
tapioca_the_moviedb/resource_mapping.py
tapioca_the_moviedb/tapioca_the_moviedb.py
tapioca_the_moviedb-0.1.1.dist-info/METADATA
tapioca_the_moviedb-0.1.1.dist-info/RECORD
tapioca_the_moviedb-0.1.1.dist-info/WHEEL
tapioca_the_moviedb-0.1.1.dist-info/top_level.txt
