Metadata-Version: 2.1
Name: tapioca-the-moviedb
Version: 0.1.1
Summary: The MovieDB API wrapper using tapioca
Home-page: https://github.com/gtsalles/tapioca-the-moviedb
Author: Gustavo Carvalho
Author-email: gtcarvalho@protonmail.com
License: MIT
Keywords: the-moviedb
Platform: UNKNOWN
Classifier: Development Status :: 5 - Production/Stable
Classifier: Intended Audience :: Developers
Classifier: License :: OSI Approved :: MIT License
Classifier: Natural Language :: English
Classifier: Programming Language :: Python :: 2
Classifier: Programming Language :: Python :: 2.7
Classifier: Programming Language :: Python :: 3
Classifier: Programming Language :: Python :: 3.1
Classifier: Programming Language :: Python :: 3.2
Classifier: Programming Language :: Python :: 3.3
Classifier: Programming Language :: Python :: 3.4
Classifier: Programming Language :: Python :: 3.5
Classifier: Programming Language :: Python :: 3.6
Classifier: Programming Language :: Python :: 3.7
Requires-Dist: tapioca-wrapper (<2)
